DbConnection/BaseClassConnectionCreator.py
DbConnection/DbConnectionCreator.py
DbConnection/OracleDbConnectionCreator.py
DbConnection/SqlAlchemyConnectionCreator.py
DbConnection/__init__.py
DbConnection-0.0.4.dist-info/Licence
DbConnection-0.0.4.dist-info/METADATA
DbConnection-0.0.4.dist-info/WHEEL
DbConnection-0.0.4.dist-info/top_level.txt
DbConnection-0.0.4.dist-info/RECORD
