Metadata-Version: 2.1
Name: DbConnection
Version: 0.0.4
Summary: Convenient wrapper to create database connection engine based on the parameters passed. This engine can be used to run sql queries on the respective databases.
Home-page: 
Download-URL: 
Author: Mallikarjuna Devaraya
License: MIT
Classifier: Development Status :: 4 - Beta
Classifier: Intended Audience :: Developers
Classifier: Topic :: Software Development :: Build Tools
Classifier: License :: OSI Approved :: MIT License
Classifier: Programming Language :: Python :: 3.8
License-File: Licence
Requires-Dist: SQLAlchemy (==1.4.25)
Requires-Dist: urllib3 (==1.26.7)
Requires-Dist: pyodbc (==4.0.34)
Requires-Dist: psycopg2 (==2.9.3)
Requires-Dist: cx-Oracle (==8.3.0)
Requires-Dist: oracledb (==1.0.3)
